nlp2go/__init__.py
nlp2go/cli.py
nlp2go/main.py
nlp2go/model.py
nlp2go/modelhub.py
nlp2go/parser.py
nlp2go/preload.py
nlp2go/server.py
nlp2go/util.py
nlp2go/test/__init__.py
nlp2go/test/test_main.py
nlp2go/test/test_model.py
nlp2go-0.4.16.dist-info/LICENSE
nlp2go-0.4.16.dist-info/METADATA
nlp2go-0.4.16.dist-info/WHEEL
nlp2go-0.4.16.dist-info/entry_points.txt
nlp2go-0.4.16.dist-info/top_level.txt
nlp2go-0.4.16.dist-info/RECORD
