Metadata-Version: 2.1
Name: nlp2go
Version: 0.4.16
Summary: hosting nlp models for demo purpose
Home-page: https://github.com/voidful/nlp2go
Author: Voidful
Author-email: voidful.stack@gmail.com
License: UNKNOWN
Keywords: nlp tfkit classification generation tagging deep learning machine reading
Platform: UNKNOWN
License-File: LICENSE
Requires-Dist: nlp2 (>=1.8.31)
Requires-Dist: tfkit (>=0.7.34)
Requires-Dist: flask
Requires-Dist: Flask-Caching
Requires-Dist: flask-cors
Requires-Dist: gevent
Requires-Dist: inquirer
Requires-Dist: transformers (>=3.3.0)
